{"id":"lTra","dependencies":[{"name":"F:\\host\\person\\vue-layer\\node_modules\\core-js\\package.json","includedInParent":true,"mtime":1535357029878},{"name":"F:\\host\\person\\vue-layer\\package.json","includedInParent":true,"mtime":1535419199547},{"name":"F:\\host\\person\\vue-layer\\.babelrc","includedInParent":true,"mtime":1535418919547}],"generated":{"js":"var $lTra$exports={};$lTra$exports=function(r){if(null==r)throw TypeError(\"Can't call method on  \"+r);return r};","map":null},"hash":"b0469a60fb48b708fa9e8eed127bda0a","cacheData":{"env":{},"imports":{},"exports":{},"wildcards":[],"isCommonJS":true}}